{
    "mangas": [
        {
            "id": "",
            "name": "",
            "banner": "https://raw.githubusercontent.com/Nyyu/TCC/main/preview/default-banner.png",
            "bannerSmall": "https://raw.githubusercontent.com/Nyyu/TCC/main/preview/default-display.png",
            "chapters": [
                {
                    "title": "",
                    "strip": []
                }
            ],
            "rating": {
                "totalRating": "",
                "totalUsers": ""
            },
            "status": "0, 1, 2, 3",
            "others": {
                "synopsis": "",
                "tags": []
            }
        }
    ]
}
